{
  "name": "9A91",
  "description": "",
  "type": "automatic",
  "how_to_get": [
  ],
  "where_using": [
  ],
  "stats": {
    "id": 12345,
    "shootTimeDown": 2,
    "damage": 7.5,
    "ammo": 20,
    "itemAmmoName": "9x39",
    "ammoList": [
      "9x39",
      "9x39pb"
    ],
    "tickReloadMax": 30.0,
    "distance": 90.0,
    "effectiveDistance": 42.5,
    "accuracy": 0.2,
    "recoilVertical": 1.3,
    "recoilHorizontal": 0.6,
    "name": "9a91",
    "localName": "9А-91",
    "shootSound": "9a91fire",
    "reloadSound": "9a91reload",
    "silencerSound": "silencersound",
    "isAuto": true,
    "description": "Описание 9a91",
    "mods": [
    ]
  },
  "icon": "",
  "price_to_sell": ""
}
